pharmacokinetics/__init__.py
pharmacokinetics/_handlers/__init__.py
pharmacokinetics/multiple_doses/__init__.py
pharmacokinetics/multiple_doses/cmax.py
pharmacokinetics/multiple_doses/recommended.py
pharmacokinetics/shared_formulas/__init__.py
pharmacokinetics/shared_formulas/concentration.py
pharmacokinetics/shared_formulas/halflife.py
pharmacokinetics/shared_formulas/tmax.py
pharmacokinetics/single_dose/__init__.py
pharmacokinetics/single_dose/concentration.py
pharmacokinetics/single_dose/halflife.py
pharmacokinetics-0.1.dist-info/LICENSE
pharmacokinetics-0.1.dist-info/METADATA
pharmacokinetics-0.1.dist-info/WHEEL
pharmacokinetics-0.1.dist-info/top_level.txt
pharmacokinetics-0.1.dist-info/RECORD
