Metadata-Version: 2.1
Name: pharmacokinetics
Version: 0.1
Summary: Python tools for pharmacokinetic calculations.
Home-page: https://github.com/xyzpw/pharmacokinetics-module/
Author: xyzpw
License: MIT
Keywords: pharmacokinetics,pharmacodynamics,pharmacology,pharmacy,chemistry
Classifier: Programming Language :: Python :: 3.10
Classifier: Programming Language :: Python :: 3.11
Classifier: Programming Language :: Python :: 3.12
Classifier: Topic :: Utilities
Classifier: License :: OSI Approved :: MIT License
Classifier: Environment :: Console
Classifier: Intended Audience :: Developers
Classifier: Intended Audience :: Science/Research
License-File: LICENSE
